empyrebase/__init__.py
empyrebase/empyrebase.py
empyrebase/services/__init__.py
empyrebase/services/auth.py
empyrebase/services/database.py
empyrebase/services/firestore.py
empyrebase/services/storage.py
empyrebase/types/__init__.py
empyrebase/types/closable_sseclient.py
empyrebase/types/firestore.py
empyrebase/types/geopoint.py
empyrebase/types/keep_auth_session.py
empyrebase/types/private.py
empyrebase/types/pyre.py
empyrebase/types/pyre_response.py
empyrebase/types/sseclient.py
empyrebase/types/stream.py
empyrebase/utils/__init__.py
empyrebase-2.4.1.dist-info/licenses/LICENSE
images/empyrebase-logo.png
empyrebase-2.4.1.dist-info/METADATA
empyrebase-2.4.1.dist-info/WHEEL
empyrebase-2.4.1.dist-info/top_level.txt
empyrebase-2.4.1.dist-info/RECORD
