Metadata-Version: 2.4
Name: empyrebase
Version: 2.4.1
Summary: A simple python wrapper for the Firebase API with current deps. Includes Realtime Database, Firestore, Authentication, and Storage.
Home-page: https://github.com/emrothenberg/empyrebase
Author: emrothenberg
License: Copyright © 2025 Eitan Rothenberg (emrothenberg)
Project-URL: Homepage, https://github.com/emrothenberg/empyrebase
Keywords: Firebase,Pyrebase,Google,Empyrebase,data,database,client,client-side,firestore,realtime,real-time,storage,authentication,auth,stream,firebase-auth,firebase-database,firebase-storage,firebase-functions,firebase-firestore,NoSQL,REST,OAuth,JWT,user-management,serverless,event-driven,cloud,auto-update,token-refresh,CRUD,realtime-stream
Classifier: Development Status :: 4 - Beta
Classifier: Intended Audience :: Developers
Classifier: License :: OSI Approved :: MIT License
Classifier: Programming Language :: Python :: 3.11
Requires-Python: >=3.11
License-File: LICENSE
Requires-Dist: requests-toolbelt>=1.0.0
Requires-Dist: requests>=2.31
Requires-Dist: urllib3>=1.21.1
Requires-Dist: google-cloud-storage>=2.18.2
Requires-Dist: google-auth>=2.38.0
Requires-Dist: pyjwt>=2.8.0
Requires-Dist: pycryptodome>=3.6.4
Requires-Dist: packaging>=24.2
Requires-Dist: web-browser>=0.0.1
Dynamic: home-page
Dynamic: license-file
